{
  "schemaVersion": 1,
  "language": "en",
  "page": "rfps",
  "title": "RFPs",
  "description": "Lorem ipsum dolor sit amet consectetur. Risus ut sollicitudin tortor aliquet sed. Consequat vestibulum lacus mauris mauris.",
  "breadcrumbLabel": "RFPs",
  "submitCta": {
    "label": "Submit an idea",
    "href": "https://discord.gg/logosnetwork",
    "external": true
  },
  "defaultView": "grid",
  "pageSize": 12,
  "pagination": {
    "previousLabel": "Previous",
    "nextLabel": "Next"
  },
  "bottomCta": {
    "title": "Have a build idea worth funding?",
    "cta": {
      "label": "Submit an RFP",
      "href": "https://discord.gg/logosnetwork",
      "external": true
    }
  }
}
